AUTHORS.rst
CONTRIBUTING.rst
HISTORY.rst
LICENSE
MANIFEST.in
README.rst
setup.cfg
setup.py
docs/Makefile
docs/authors.rst
docs/conf.py
docs/contributing.rst
docs/history.rst
docs/index.rst
docs/installation.rst
docs/make.bat
docs/readme.rst
docs/usage.rst
sockspy/__init__.py
sockspy/cli.py
sockspy/sockspy_main.py
sockspy.egg-info/PKG-INFO
sockspy.egg-info/SOURCES.txt
sockspy.egg-info/dependency_links.txt
sockspy.egg-info/entry_points.txt
sockspy.egg-info/not-zip-safe
sockspy.egg-info/requires.txt
sockspy.egg-info/top_level.txt
sockspy/core/__init__.py
sockspy/core/config.py
sockspy/core/context.py
sockspy/core/engine.py
sockspy/core/exceptions.py
sockspy/core/pool.py
sockspy/core/transport.py
sockspy/resources/__init__.py
sockspy/resources/log.yaml
sockspy/socket/__init__.py
sockspy/socket/raw.py
sockspy/socks_impl/__init__.py
sockspy/socks_impl/socks5.py
tests/__init__.py
tests/test_abc.py
tests/test_sockspy.py