Metadata-Version: 1.1
Name: sockspy
Version: 0.2.7
Summary: A python socks5 proxy implementation.
Home-page: https://github.com/fifman/sockspy
Author: Fifman Feng
Author-email: fifmanyc@gmail.com
License: MIT license
Keywords: sockspy
Platform: UNKNOWN
Classifier: Development Status :: 2 - Pre-Alpha
Classifier: Intended Audience :: Developers
Classifier: License :: OSI Approved :: MIT License
Classifier: Natural Language :: English
Classifier: Programming Language :: Python :: 3.4
Classifier: Programming Language :: Python :: 3.5
